reliquery/__init__.py
reliquery/metadata.py
reliquery/relic.py
reliquery/settings.py
reliquery/storage.py
reliquery-0.3.2.dist-info/LICENSE
reliquery-0.3.2.dist-info/METADATA
reliquery-0.3.2.dist-info/WHEEL
reliquery-0.3.2.dist-info/top_level.txt
reliquery-0.3.2.dist-info/RECORD
